pytha/__init__.py
pytha/main.py
pytha_fuzz-1.2.dist-info/LICENSE
pytha_fuzz-1.2.dist-info/METADATA
pytha_fuzz-1.2.dist-info/WHEEL
pytha_fuzz-1.2.dist-info/entry_points.txt
pytha_fuzz-1.2.dist-info/top_level.txt
pytha_fuzz-1.2.dist-info/RECORD
