Metadata-Version: 2.1
Name: pytha-fuzz
Version: 1.2
Summary: PYTHA is a Python-based directory fuzzer tool designed to aid in the discovery of hidden or sensitive directories and files on web servers. Originally developed by Shivang. Packed and moduled by the author.
Home-page: https://github.com/shivangmauryaa/pytha-fuzz
Author: Parth Mishra
Author-email: halfstackpgr@gmail.com
Classifier: Programming Language :: Python :: 3
Classifier: License :: OSI Approved :: MIT License
Classifier: Operating System :: OS Independent
Requires-Python: >=3.10
License-File: LICENSE
Requires-Dist: aiofiles
Requires-Dist: colorama
Requires-Dist: aiohttp
